setup.py
tkgtools/__init__.py
tkgtools/tkgtools.py
tkgtools.egg-info/PKG-INFO
tkgtools.egg-info/SOURCES.txt
tkgtools.egg-info/dependency_links.txt
tkgtools.egg-info/top_level.txt