Metadata-Version: 1.2
Name: tkgtools
Version: 0.19.6.2
Summary: tkgtools is created by George Zhao, who is working for NOKIA, 2010-2012, 2014-2019.
Home-page: http://not-available.now
Author: George Zhao
Author-email: georgezhao_1980@163.com
Maintainer: George Zhao
Maintainer-email: georgezhao_1980@163.com
License: BSD License
Platform: all
Classifier: Development Status :: 3 - Alpha
Classifier: Operating System :: OS Independent
Classifier: Intended Audience :: Developers
Classifier: License :: OSI Approved :: BSD License
Classifier: Programming Language :: Python :: 3.6
Classifier: Topic :: Software Development :: Libraries
